py_mp-1.2.dist-info/METADATA
py_mp-1.2.dist-info/RECORD
py_mp-1.2.dist-info/WHEEL
py_mp-1.2.dist-info/entry_points.txt
py_mp-1.2.dist-info/top_level.txt
pymp/__init__.py
pymp/__main__.py
pymp/helper.py
pymp/player.py
pymp/song.py
